cubox/__init__.py
cubox/cubox_api.py
cubox-1.0.0.dist-info/LICENSE
cubox-1.0.0.dist-info/METADATA
cubox-1.0.0.dist-info/WHEEL
cubox-1.0.0.dist-info/RECORD
